LICENSE.txt
MANIFEST.in
README.rst
preconditions.py
setup.py
tests.py
preconditions.egg-info/PKG-INFO
preconditions.egg-info/SOURCES.txt
preconditions.egg-info/dependency_links.txt
preconditions.egg-info/top_level.txt