Metadata-Version: 1.0
Name: preconditions
Version: 0.1
Summary: Flexible, concise preconditions.
Home-page: https://github.com/nejucomo/preconditions
Author: Nathan Wilcox
Author-email: nejucomo@gmail.com
License: MIT
Platform: UNKNOWN
